{
  "fed-press-all": {
    "label": "Federal Reserve press releases",
    "status": 304,
    "fetchedAt": "2026-04-10T16:00:04+00:00",
    "fetchedItems": 0,
    "etag": "W/\"ddae119231c8dc1:0\"",
    "lastModified": "Thu, 09 Apr 2026 15:00:14 GMT",
    "error": null,
    "durationMs": 0
  },
  "sec-press-releases": {
    "label": "SEC press releases",
    "status": 200,
    "fetchedAt": "2026-04-10T16:00:04+00:00",
    "fetchedItems": 25,
    "etag": "\"1775836705\"",
    "lastModified": "Fri, 10 Apr 2026 15:58:25 GMT",
    "error": null,
    "durationMs": 0
  },
  "bls-macro-google-news": {
    "label": "Google News: BLS macro releases",
    "status": 200,
    "fetchedAt": "2026-04-10T16:00:05+00:00",
    "fetchedItems": 100,
    "etag": null,
    "lastModified": null,
    "error": null,
    "durationMs": 1000
  },
  "treasury-press-google-news": {
    "label": "Google News: Treasury press releases",
    "status": 200,
    "fetchedAt": "2026-04-10T16:00:06+00:00",
    "fetchedItems": 100,
    "etag": null,
    "lastModified": null,
    "error": null,
    "durationMs": 1000
  },
  "yahoo-finance-news": {
    "label": "Yahoo Finance news",
    "status": 200,
    "fetchedAt": "2026-04-10T16:00:06+00:00",
    "fetchedItems": 48,
    "etag": "\"f00af51113f7c4d47e81f4b450aad8da\"",
    "lastModified": "Fri, 10 Apr 2026 15:51:01 GMT",
    "error": null,
    "durationMs": 0
  },
  "cnbc-us-top-news": {
    "label": "CNBC US top news and analysis",
    "status": 200,
    "fetchedAt": "2026-04-10T16:00:06+00:00",
    "fetchedItems": 30,
    "etag": null,
    "lastModified": null,
    "error": null,
    "durationMs": 0
  }
}
